[{"nombre":"INVESTIGACIÓN","codigo":"617002","creditos":"6"},{"nombre":"MEDICINA FÍSICA Y REHABILITACIÓN I.","codigo":"617004","creditos":"44"},{"nombre":"MEDICINA FÍSICA Y REHABILITACIÓN II.","codigo":"617005","creditos":"21"},{"nombre":"MEDICINA FÍSICA Y REHABILITACIÓN","codigo":"617005M","creditos":"2"},{"nombre":"MEDICINA FÍSICA Y REHABILITACIÓN III.","codigo":"617006","creditos":"30"},{"nombre":"DOLOR","codigo":"617006M","creditos":"5"},{"nombre":"ÓRTESIS PRÓTESIS TECNOLOGÍA ASISTENCIA I","codigo":"617007","creditos":"7"},{"nombre":"ÓRTESIS PRÓTESIS TECNOLOG ASISTENCIA II","codigo":"617008","creditos":"3"},{"nombre":"ÓRTESIS PRÓTESIS TECNOLOG ASISTENCIA III","codigo":"617009","creditos":"4"},{"nombre":"ANATOMÍA Y KINESIOLOGÍA APLICADAS","codigo":"617010","creditos":"6"},{"nombre":"ELECTRODIAGNÓSTICO I","codigo":"617011","creditos":"3"},{"nombre":"FISIATRÍA - MEDICINA FAMILIAR","codigo":"617012","creditos":"7"},{"nombre":"ELECTRODIAGNÓSTICO II","codigo":"617182","creditos":"8"},{"nombre":"ELECTRODIAGNÓSTICO III","codigo":"617183","creditos":"10"},{"nombre":"MEDICINA FÍSICA Y REHABILITACIÓN","codigo":"617184","creditos":"5"},{"nombre":"REHABILITACIÓN CARDIACA","codigo":"617810","creditos":"5"},{"nombre":"ELECTIVA","codigo":"617811","creditos":"7"}]